pyleiter/__init__.py
pyleiter/__main__.py
pyleiter/cli.py
pyleiter/config.py
pyleiter/errors.py
pyleiter/runner.py
pyleiter-0.2.1.dist-info/LICENSE
pyleiter-0.2.1.dist-info/METADATA
pyleiter-0.2.1.dist-info/WHEEL
pyleiter-0.2.1.dist-info/entry_points.txt
pyleiter-0.2.1.dist-info/RECORD
